[
    {
        "biolink_block_id": "3",
        "location_url": "https:\/\/w.alooytv2.xyz\/tv-series.html"
    },
    {
        "biolink_block_id": "10",
        "location_url": "https:\/\/w.alooytv2.xyz\/genre\/ramadan-kleeji-2025.html"
    },
    {
        "biolink_block_id": "11",
        "location_url": "https:\/\/w.alooytv2.xyz\/genre\/ramadan-arabi-2025.html"
    },
    {
        "biolink_block_id": "12",
        "location_url": "https:\/\/w.alooytv2.xyz\/genre\/turki.html"
    },
    {
        "biolink_block_id": "13",
        "location_url": "https:\/\/w.alooytv2.xyz\/genre\/farisi.html"
    }
]